jirafs_csv_table/__init__.py
jirafs_csv_table/plugin.py
jirafs_csv_table-1.0.2.dist-info/LICENSE
jirafs_csv_table-1.0.2.dist-info/METADATA
jirafs_csv_table-1.0.2.dist-info/WHEEL
jirafs_csv_table-1.0.2.dist-info/entry_points.txt
jirafs_csv_table-1.0.2.dist-info/top_level.txt
jirafs_csv_table-1.0.2.dist-info/RECORD
